mediforge/__init__.py
mediforge/cli.py
mediforge/backends/__init__.py
mediforge/backends/executor.py
mediforge/backends/ffmpeg.py
mediforge/config/__init__.py
mediforge/config/defaults.py
mediforge/config/loader.py
mediforge/core/__init__.py
mediforge/core/errors.py
mediforge/core/models.py
mediforge/core/probe.py
mediforge/core/scenario.py
mediforge/core/timecode.py
mediforge/plugins/__init__.py
mediforge/plugins/audio/__init__.py
mediforge/plugins/audio/compose.py
mediforge/plugins/audio/master.py
mediforge/plugins/audio/normalize.py
mediforge/plugins/info/__init__.py
mediforge/plugins/mux/__init__.py
mediforge/plugins/video/__init__.py
mediforge/plugins/video/compose.py
mediforge/utils/__init__.py
mediforge/utils/logging.py
mediforge/utils/tempfiles.py
mediforge-0.7.6.dist-info/METADATA
mediforge-0.7.6.dist-info/WHEEL
mediforge-0.7.6.dist-info/entry_points.txt
mediforge-0.7.6.dist-info/licenses/LICENSE
mediforge-0.7.6.dist-info/RECORD
