Metadata-Version: 2.4
Name: mediforge
Version: 0.7.6
Summary: Command-line media processing toolkit
Author: stayen
License: MIT
License-File: LICENSE
Keywords: audio,cli,ffmpeg,media,video
Classifier: Development Status :: 4 - Beta
Classifier: Environment :: Console
Classifier: Intended Audience :: End Users/Desktop
Classifier: License :: OSI Approved :: MIT License
Classifier: Operating System :: OS Independent
Classifier: Programming Language :: Python :: 3
Classifier: Programming Language :: Python :: 3.11
Classifier: Programming Language :: Python :: 3.12
Classifier: Topic :: Multimedia :: Sound/Audio
Classifier: Topic :: Multimedia :: Video
Requires-Python: >=3.11
Requires-Dist: click>=8.0
Requires-Dist: pydantic>=2.0
Requires-Dist: rich>=13.0
Requires-Dist: ruamel-yaml>=0.18
Provides-Extra: dev
Requires-Dist: mypy>=1.0; extra == 'dev'
Requires-Dist: pytest-cov>=4.0; extra == 'dev'
Requires-Dist: pytest>=7.0; extra == 'dev'
Requires-Dist: ruff>=0.1; extra == 'dev'
